pulumi_okta/__init__.py
pulumi_okta/_inputs.py
pulumi_okta/_utilities.py
pulumi_okta/admin_role_custom.py
pulumi_okta/admin_role_custom_assignments.py
pulumi_okta/admin_role_targets.py
pulumi_okta/api_service_integration.py
pulumi_okta/api_token.py
pulumi_okta/app_group_assignments.py
pulumi_okta/app_oauth_api_scope.py
pulumi_okta/app_saml_app_settings.py
pulumi_okta/app_shared_credentials.py
pulumi_okta/app_signon_policy.py
pulumi_okta/app_signon_policy_rule.py
pulumi_okta/app_user_base_schema_property.py
pulumi_okta/app_user_schema_property.py
pulumi_okta/auth_server_claim_default.py
pulumi_okta/auth_server_default.py
pulumi_okta/authenticator.py
pulumi_okta/behaviour.py
pulumi_okta/brand.py
pulumi_okta/campaign.py
pulumi_okta/captcha.py
pulumi_okta/captcha_org_wide_settings.py
pulumi_okta/customized_signin_page.py
pulumi_okta/device.py
pulumi_okta/domain.py
pulumi_okta/domain_certificate.py
pulumi_okta/domain_verification.py
pulumi_okta/email_customization.py
pulumi_okta/email_domain.py
pulumi_okta/email_domain_verification.py
pulumi_okta/email_sender.py
pulumi_okta/email_sender_verification.py
pulumi_okta/email_smtp_server.py
pulumi_okta/email_template_settings.py
pulumi_okta/end_user_my_requests.py
pulumi_okta/entitlement.py
pulumi_okta/entitlement_bundle.py
pulumi_okta/event_hook.py
pulumi_okta/event_hook_verification.py
pulumi_okta/factor_totp.py
pulumi_okta/feature.py
pulumi_okta/get_api_service_integration.py
pulumi_okta/get_api_token.py
pulumi_okta/get_app_group_assignments.py
pulumi_okta/get_app_signon_policy.py
pulumi_okta/get_app_user_assignments.py
pulumi_okta/get_apps.py
pulumi_okta/get_auth_server_claim.py
pulumi_okta/get_auth_server_claims.py
pulumi_okta/get_authenticator.py
pulumi_okta/get_behaviour.py
pulumi_okta/get_behaviours.py
pulumi_okta/get_brand.py
pulumi_okta/get_brands.py
pulumi_okta/get_campaign.py
pulumi_okta/get_catalog_entry_default.py
pulumi_okta/get_catalog_entry_user_access_request_fields.py
pulumi_okta/get_default_signin_page.py
pulumi_okta-6.2.1.dist-info/METADATA
pulumi_okta-6.2.1.dist-info/WHEEL
pulumi_okta-6.2.1.dist-info/top_level.txt
pulumi_okta-6.2.1.dist-info/RECORD
